ubiwear/__init__.py
ubiwear/dataset.py
ubiwear/processor.py
ubiwear/window.py
ubiwear-0.0.16.dist-info/LICENSE
ubiwear-0.0.16.dist-info/METADATA
ubiwear-0.0.16.dist-info/WHEEL
ubiwear-0.0.16.dist-info/top_level.txt
ubiwear-0.0.16.dist-info/RECORD
