Metadata-Version: 2.1
Name: ubiwear
Version: 0.0.16
Summary: A Python library for pre-processing ubiquitous aggregated self-tracking data
Home-page: https://github.com/stergiosbamp/deep-physical-activity-prediction/ubiwear/
Author: Stergios Bampakis
Author-email: bampakis.stergios@gmail.com
License: UNKNOWN
Platform: UNKNOWN
Classifier: Programming Language :: Python :: 3.8
Classifier: Development Status :: 3 - Alpha
Classifier: Operating System :: OS Independent
Requires-Python: >=3.8
License-File: LICENSE
Requires-Dist: pandas
Requires-Dist: scikit-learn
